main/__init__.py
main/admin.py
main/apps.py
main/models.py
main/tests.py
main/views.py
main/static/main/css/custom.css
main/static/main/css/fontastic.css
main/static/main/css/grasp_mobile_progress_circle-1.0.0.min.css
main/static/main/css/highchart.css
main/static/main/css/print.css
main/static/main/css/select2.min.css
main/static/main/css/style.blue.css
main/static/main/css/style.default.css
main/static/main/css/style.green.css
main/static/main/css/style.pink.css
main/static/main/css/style.red.css
main/static/main/css/style.sea.css
main/static/main/css/style.violet.css
main/static/main/css/table_print.css
main/static/main/css/chart/all.css
main/static/main/css/chart/emp_unit.css
main/static/main/css/leaflet/leaflet.css
main/static/main/data/addresses.json
main/static/main/data/countries.json
main/static/main/fonts/dashboard.eot
main/static/main/fonts/dashboard.svg
main/static/main/fonts/dashboard.ttf
main/static/main/fonts/dashboard.woff
main/static/main/icons-reference/icons-reference.html
main/static/main/icons-reference/styles.css
main/static/main/icons-reference/fonts/dashboard.eot
main/static/main/icons-reference/fonts/dashboard.svg
main/static/main/icons-reference/fonts/dashboard.ttf
main/static/main/icons-reference/fonts/dashboard.woff
main/static/main/images/adn.png
main/static/main/images/all.png
main/static/main/images/banner.jpg
main/static/main/images/computer.png
main/static/main/images/error_404.jpg
main/static/main/images/error_500.jpg
main/static/main/images/favicon.png
main/static/main/images/favicon2.png
main/static/main/images/female.png
main/static/main/images/ipg.png
main/static/main/images/man.jpg
main/static/main/images/man.png
main/static/main/images/mop_adn_logo.jpg
main/static/main/images/mpm.png
main/static/main/images/mpo.png
main/static/main/images/rdtl.jpg
main/static/main/images/science.png
main/static/main/images/woman.jpg
main/static/main/js/charts-custom.js
main/static/main/js/charts-home.js
main/static/main/js/datatable_custom.js
django_ipghrms_main-1.6.dist-info/LICENSE
django_ipghrms_main-1.6.dist-info/METADATA
django_ipghrms_main-1.6.dist-info/WHEEL
django_ipghrms_main-1.6.dist-info/top_level.txt
django_ipghrms_main-1.6.dist-info/RECORD
